pyreach/__init__.py
pyreach/exceptions.py
pyreach-1.0.0.dist-info/licenses/LICENSE
pyreach-1.0.0.dist-info/METADATA
pyreach-1.0.0.dist-info/WHEEL
pyreach-1.0.0.dist-info/top_level.txt
pyreach-1.0.0.dist-info/RECORD
