Metadata-Version: 2.4
Name: pyreach
Version: 1.0.0
Summary: Python wrapper for Reach API
Home-page: https://github.com/EmeraldAnalytics/pyreach
Author: mdunndata
Classifier: License :: OSI Approved :: BSD License
Classifier: Programming Language :: Python :: 3 :: Only
License-File: LICENSE
Requires-Dist: requests
Requires-Dist: tenacity
Dynamic: author
Dynamic: classifier
Dynamic: description-content-type
Dynamic: home-page
Dynamic: license-file
Dynamic: requires-dist
Dynamic: summary
